gui_converter/__init__.py
gui_converter/__main__.py
gui_converter-1.0.0.dist-info/LICENSE
gui_converter-1.0.0.dist-info/METADATA
gui_converter-1.0.0.dist-info/WHEEL
gui_converter-1.0.0.dist-info/entry_points.txt
gui_converter-1.0.0.dist-info/top_level.txt
gui_converter-1.0.0.dist-info/RECORD
