Metadata-Version: 2.1
Name: gui-converter
Version: 1.0.0
Summary: GUI Converter Tool for KotOR - converts GUI files between games
Author: NickHugi
Maintainer-email: th3w1zard1 <halomastar@gmail.com>
License: LGPL-3.0-or-later
Project-URL: Homepage, https://github.com/th3w1zard1/PyKotor
Project-URL: Documentation, https://github.com/th3w1zard1/PyKotor/wiki
Project-URL: Repository, https://github.com/th3w1zard1/PyKotor.git
Project-URL: Issues, https://github.com/th3w1zard1/PyKotor/issues
Project-URL: Changelog, https://github.com/th3w1zard1/PyKotor/releases
Keywords: kotor,kotor1,kotor2,tsl,gui,converter,interface,pykotor,modding
Classifier: Development Status :: 4 - Beta
Classifier: Intended Audience :: Developers
Classifier: License :: OSI Approved :: GNU Lesser General Public License v3 or later (LGPLv3+)
Classifier: Operating System :: OS Independent
Classifier: Programming Language :: Python :: 3
Classifier: Programming Language :: Python :: 3.8
Classifier: Programming Language :: Python :: 3.9
Classifier: Programming Language :: Python :: 3.10
Classifier: Programming Language :: Python :: 3.11
Classifier: Programming Language :: Python :: 3.12
Classifier: Topic :: Games/Entertainment
Classifier: Topic :: Utilities
Classifier: Environment :: Console
Requires-Python: >=3.8
License-File: LICENSE
Requires-Dist: pykotor>=2.0.0
Provides-Extra: dev
Requires-Dist: pytest>=7.0.0; extra == "dev"
Requires-Dist: ruff>=0.1.0; extra == "dev"
